pyuul_kmeans/VolumeMaker.py
pyuul_kmeans/__init__.py
pyuul_kmeans/utils.py
pyuul_kmeans/sources/__init__.py
pyuul_kmeans/sources/globalVariables.py
pyuul_kmeans/sources/hashings.py
pyuul_kmeans-0.0.2.dist-info/LICENSE
pyuul_kmeans-0.0.2.dist-info/METADATA
pyuul_kmeans-0.0.2.dist-info/WHEEL
pyuul_kmeans-0.0.2.dist-info/top_level.txt
pyuul_kmeans-0.0.2.dist-info/RECORD
